b4_backup/__init__.py
b4_backup/__main__.py
b4_backup/cli/__init__.py
b4_backup/cli/init.py
b4_backup/cli/main.py
b4_backup/cli/tools.py
b4_backup/cli/utils.py
b4_backup/config_schema.py
b4_backup/default_logging_config.yml
b4_backup/exceptions.py
b4_backup/main/__init__.py
b4_backup/main/b4_backup.py
b4_backup/main/backup_target_host.py
b4_backup/main/connection.py
b4_backup/main/dataclass.py
b4_backup/utils.py
b4_backup-1.4.0.dist-info/METADATA
b4_backup-1.4.0.dist-info/WHEEL
b4_backup-1.4.0.dist-info/entry_points.txt
b4_backup-1.4.0.dist-info/RECORD
